setup.cfg
setup.py
lddya/Analysis.py
lddya/Data.py
lddya/DataFrame.py
lddya/Draw.py
lddya/Map.py
lddya/Optimizer.py
lddya/__init__.py
lddya/tool.py
lddya.egg-info/PKG-INFO
lddya.egg-info/SOURCES.txt
lddya.egg-info/dependency_links.txt
lddya.egg-info/requires.txt
lddya.egg-info/top_level.txt
lddya/Algorithm/Heuristic.py
lddya/Algorithm/Traditional.py