Metadata-Version: 2.1
Name: lddya
Version: 5.5.0
Summary: 1.新增数据分析模块。
Home-page: https://github.com/not_define/please_wait
Author: lidongdong
Author-email: 927052521@qq.com
License: MIT Licence
Keywords: licensetool,pip,gm,license,tool
Platform: any
